arduscope/__init__.py
arduscope/arduscope.ino
arduscope/arduscope.py
arduscope/fit_tools.py
arduscope/wave_generator.py
arduscope-0.3.3.dist-info/LICENSE
arduscope-0.3.3.dist-info/METADATA
arduscope-0.3.3.dist-info/WHEEL
arduscope-0.3.3.dist-info/top_level.txt
arduscope-0.3.3.dist-info/zip-safe
arduscope-0.3.3.dist-info/RECORD
