Metadata-Version: 2.1
Name: arduscope
Version: 0.3.3
Summary: Un osciloscopio basado en Arduino + Python y orientado a laboratorios de enseñanza
Home-page: https://github.com/alemazzeo/arduscope.git
Author: Alejandro Ezequiel Mazzeo
Author-email: ale.exactas@gmail.com
License: UNKNOWN
Platform: UNKNOWN
Classifier: Development Status :: 4 - Beta
Classifier: License :: OSI Approved :: MIT License
Requires-Python: >=3.6
License-File: LICENSE
Requires-Dist: numpy
Requires-Dist: scipy
Requires-Dist: matplotlib
Requires-Dist: pyserial
Requires-Dist: tqdm
